tgadmin/__init__.py
tgadmin/imex.py
tgadmin/tgadmin.py
tgadmin/tgimport.py
tgadmin/utils.py
tgadmin/linkrewrite-specs/INDEX.txt
tgadmin/linkrewrite-specs/INDEX.txt.license
tgadmin/linkrewrite-specs/collate.xml
tgadmin/linkrewrite-specs/epub.xml
tgadmin/linkrewrite-specs/html.xml
tgadmin/linkrewrite-specs/schema.xml
tgadmin/linkrewrite-specs/tei.xml
tgadmin/linkrewrite-specs/textgrid.xml
tgadmin-0.38.1.dist-info/licenses/LICENSE
tgadmin-0.38.1.dist-info/METADATA
tgadmin-0.38.1.dist-info/WHEEL
tgadmin-0.38.1.dist-info/entry_points.txt
tgadmin-0.38.1.dist-info/top_level.txt
tgadmin-0.38.1.dist-info/RECORD
