Metadata-Version: 2.4
Name: tgadmin
Version: 0.38.1
Summary: TextGrid repository administration cli tool, based on tgclients
Author-email: Ubbo Veentjer <veentjer@sub.uni-goettingen.de>
Maintainer-email: Ubbo Veentjer <veentjer@sub.uni-goettingen.de>
License:                    GNU LESSER GENERAL PUBLIC LICENSE
Project-URL: Homepage, https://textgrid.de
Project-URL: Issues, https://gitlab.gwdg.de/dariah-de/textgridrep/tgadmin/-/issues
Project-URL: Source, https://gitlab.gwdg.de/dariah-de/textgridrep/tgadmin
Classifier: Development Status :: 3 - Alpha
Classifier: Intended Audience :: Science/Research
Classifier: License :: OSI Approved :: GNU Lesser General Public License v3 (LGPLv3)
Classifier: Operating System :: OS Independent
Classifier: Programming Language :: Python :: 3
Requires-Python: <3.14,>=3.8
License-File: LICENSE
Requires-Dist: click
Requires-Dist: rich-click
Requires-Dist: tgclients==0.22.0
Provides-Extra: dev
Requires-Dist: reuse; extra == "dev"
Requires-Dist: ruff; extra == "dev"
Requires-Dist: pydoclint; extra == "dev"
Requires-Dist: pip-tools; extra == "dev"
Requires-Dist: pytest; extra == "dev"
Requires-Dist: pytest-datadir; extra == "dev"
Requires-Dist: coverage; extra == "dev"
Requires-Dist: pre-commit; extra == "dev"
Dynamic: license-file
